LICENSE.md
README.md
pyproject.toml
src/ewoksid02/__init__.py
src/ewoksid02.egg-info/PKG-INFO
src/ewoksid02.egg-info/SOURCES.txt
src/ewoksid02.egg-info/dependency_links.txt
src/ewoksid02.egg-info/entry_points.txt
src/ewoksid02.egg-info/requires.txt
src/ewoksid02.egg-info/top_level.txt
src/ewoksid02/ocl/__init__.py
src/ewoksid02/resources/__init__.py
src/ewoksid02/resources/saxs_loop.json
src/ewoksid02/resources/template_saxs.yaml
src/ewoksid02/scripts/__init__.py
src/ewoksid02/scripts/__main__.py
src/ewoksid02/scripts/parsers.py
src/ewoksid02/scripts/utils.py
src/ewoksid02/scripts/saxs/__init__.py
src/ewoksid02/scripts/saxs/main.py
src/ewoksid02/scripts/saxs/slurm_python_post_script.py
src/ewoksid02/scripts/saxs/slurm_python_pre_script.py
src/ewoksid02/scripts/xpcs/__init__.py
src/ewoksid02/scripts/xpcs/__main__.py
src/ewoksid02/tasks/__init__.py
src/ewoksid02/tasks/averagetask.py
src/ewoksid02/tasks/azimuthaltask.py
src/ewoksid02/tasks/cavingtask.py
src/ewoksid02/tasks/id02processingtask.py
src/ewoksid02/tasks/looptask.py
src/ewoksid02/tasks/normalizationtask.py
src/ewoksid02/tasks/scalerstask.py
src/ewoksid02/tasks/secondaryscatteringtask.py
src/ewoksid02/tasks/sumtask.py
src/ewoksid02/tests/__init__.py
src/ewoksid02/tests/conftest.py
src/ewoksid02/tests/test_2scat_node.py
src/ewoksid02/tests/test_ave_node.py
src/ewoksid02/tests/test_azim_node.py
src/ewoksid02/tests/test_caving_node.py
src/ewoksid02/tests/test_norm_node.py
src/ewoksid02/tests/test_saxs.py
src/ewoksid02/tests/test_sumtask.py
src/ewoksid02/tests/utils.py
src/ewoksid02/utils/__init__.py
src/ewoksid02/utils/average.py
src/ewoksid02/utils/blissdata.py
src/ewoksid02/utils/caving.py
src/ewoksid02/utils/cupyutils.py
src/ewoksid02/utils/io.py
src/ewoksid02/utils/normalization.py
src/ewoksid02/utils/pyfai.py
src/ewoksid02/utils/secondaryscattering.py