Metadata-Version: 2.4
Name: ewoksid02
Version: 0.0.1a0
Summary: Data processing SAXS and XPCS workflows for ID02
Author-email: ESRF <edgar.gutierrez-fernandez@esrf.fr>
License: # MIT License
Project-URL: Homepage, https://gitlab.esrf.fr/workflow/ewoksapps/ewoksid02/
Project-URL: Documentation, https://ewoksid02.readthedocs.io/
Project-URL: Repository, https://gitlab.esrf.fr/workflow/ewoksapps/ewoksid02/
Project-URL: Issues, https://gitlab.esrf.fr/workflow/ewoksapps/ewoksid02/issues
Project-URL: Changelog, https://gitlab.esrf.fr/workflow/ewoksapps/ewoksid02/-/blob/main/CHANGELOG.md
Keywords: ewoks
Classifier: Intended Audience :: Science/Research
Classifier: License :: OSI Approved :: MIT License
Classifier: Programming Language :: Python :: 3
Requires-Python: >=3.8
License-File: LICENSE.md
Requires-Dist: ewoks
Requires-Dist: ewokscore
Requires-Dist: ewoksjob[blissworker]
Requires-Dist: ewoksjob[slurm]
Requires-Dist: ewoksppf
Requires-Dist: h5py
Requires-Dist: numpy<2
Requires-Dist: scipy
Requires-Dist: silx
Requires-Dist: pyfai
Requires-Dist: blissdata
Requires-Dist: numexpr!=2.8.6
Requires-Dist: psutil
Requires-Dist: pyyaml
Provides-Extra: test
Requires-Dist: pytest>=7; extra == "test"
Provides-Extra: dev
Requires-Dist: ewoksid02[test]; extra == "dev"
Requires-Dist: black>=25; extra == "dev"
Requires-Dist: flake8>=4; extra == "dev"
Provides-Extra: doc
Requires-Dist: ewoksid02[test]; extra == "doc"
Requires-Dist: sphinx>=4.5; extra == "doc"
Requires-Dist: sphinx-autodoc-typehints>=1.16; extra == "doc"
Requires-Dist: pydata-sphinx-theme; extra == "doc"
Requires-Dist: nbsphinx; extra == "doc"
Requires-Dist: ipython; extra == "doc"
Provides-Extra: cupy
Requires-Dist: cupy; extra == "cupy"
Dynamic: license-file
